spacy_train_tools/__init__.py
spacy_train_tools/command_line.py
spacy_train_tools/train.py
spacy_train_tools/utils.py
spacy_train_tools-0.1.5.dist-info/LICENSE
spacy_train_tools-0.1.5.dist-info/METADATA
spacy_train_tools-0.1.5.dist-info/WHEEL
spacy_train_tools-0.1.5.dist-info/top_level.txt
spacy_train_tools-0.1.5.dist-info/RECORD
