Metadata-Version: 2.1
Name: spacy_train_tools
Version: 0.1.5
Summary: A library to train spacy.
Home-page: https://github.com/andy1xx8/spacy-train-tools
Author: Andy Le
Author-email: tauit.dnmd@gmail.com
License: UNKNOWN
Project-URL: Bug Tracker, https://github.com/andy1xx8/spacy-train-tools/issues
Platform: UNKNOWN
Classifier: Programming Language :: Python :: 3
Classifier: License :: OSI Approved :: MIT License
Classifier: Operating System :: OS Independent
Requires-Python: >=3.6
License-File: LICENSE
